{
  "id": "cand_000707",
  "net": "f[48]_INST_0_i_7_n_0",
  "sink_cell": "f[48]_INST_0_i_6",
  "sink_pin": null,
  "target_slice": "SLICE_X109Y467",
  "lut_delay_ps": 120.0,
  "from": "f[48]_INST_0_i_7",
  "to": "f[48]_INST_0_i_6",
  "distance": 2,
  "coords": {
    "src": [
      110,
      467
    ],
    "dest": [
      108,
      467
    ]
  },
  "eco_ready": true,
  "issues": [
    "missing_sink_pin"
  ],
  "source_cell": "f[48]_INST_0_i_7",
  "source_cell_type": "LUT6",
  "sink_cell_type": "LUT6",
  "source_site": "SLICE_X110Y467",
  "sink_site": "SLICE_X108Y467"
}