{
  "id": "cand_002693",
  "net": "f[81]_INST_0_i_2/O",
  "sink_cell": "f[83]_INST_0_i_4",
  "sink_pin": null,
  "target_slice": "SLICE_X46Y427",
  "lut_delay_ps": 120.0,
  "from": "f[81]_INST_0_i_2/IBUFCTRL_INST",
  "to": "f[83]_INST_0_i_4",
  "distance": 224,
  "coords": {
    "src": [
      1,
      360
    ],
    "dest": [
      91,
      494
    ]
  },
  "eco_ready": true,
  "issues": [
    "missing_sink_pin"
  ],
  "source_cell_type": "IBUFCTRL",
  "sink_cell_type": "LUT5",
  "source_cell": "f[81]_INST_0_i_2/IBUFCTRL_INST",
  "source_site": "IOB_X1Y360",
  "sink_site": "SLICE_X91Y494"
}